01_verilog_basics/05_counter/src/counter_4bit.v
module counter_4bit(
    input clk,
    input reset,
    input en,
    output reg [3:0] count
);

    always @(posedge clk) begin
        if (reset) begin
            count <= 4'b0000;
        end else if (en) begin
            count <= count + 4'b0001;
        end else begin
            count <= count;
        end    
    end

endmodule

01_verilog_basics/05_counter/tb/counter_4bit_tb.v
`timescale 1ns/1ps

module counter_4bit_tb;

reg clk;
reg reset;
reg en;

wire [3:0] count;

reg [3:0] expected_count;

counter_4bit dut(
    .clk(clk),
    .reset(reset),
    .en(en),
    .count(count)
);

always #5 clk = ~clk;

task check_count;
    input [79:0] test_name;
    input [3:0] exp_count;

    begin
        expected_count = exp_count;

        #1

        if (count == expected_count) begin
            $display("pass | %s | time=%0t | reset=%b | en=%b | count=%b | expected_count=%b",
                         test_name, $time, reset, en, count, expected_count);
        end else begin
            $display("fail | %s | time=%0t | reset=%b | en=%b | count=%b | expected_count=%b",
                         test_name, $time, reset, en, count, expected_count);
        end
    end
endtask    

initial begin
    $dumpfile("05_counter/waves/counter_4bit.vcd");
    $dumpvars(0 , counter_4bit_tb);

    clk = 0;
    en = 0;
    reset = 1;
    expected_count = 4'b0000;

    @(posedge clk);
    check_count("reset", 4'b0000);

    en = 1;
    reset = 0;

    @(posedge clk);
    check_count("count_1", 4'b0001);

    @(posedge clk);
    check_count("count_2", 4'b0010);

    @(posedge clk);
    check_count("count_3", 4'b0011);

    en = 0;

    @(posedge clk);
    check_count("hold", 4'b0011);

    en = 1;
    reset = 1;

    @(posedge clk);
    check_count("reset", 4'b0000);

    $finish;
end

endmodule

01_verilog_basics/05_counter/waves/counter_4bit.vcd
$date
	Mon Jun 22 17:11:20 2026
$end
$version
	Icarus Verilog
$end
$timescale
	1ps
$end
$scope module counter_4bit_tb $end
$var wire 4 ! count [3:0] $end
$var reg 1 " clk $end
$var reg 1 # en $end
$var reg 4 $ expected_count [3:0] $end
$var reg 1 % reset $end
$scope module dut $end
$var wire 1 " clk $end
$var wire 1 # en $end
$var wire 1 % reset $end
$var reg 4 & count [3:0] $end
$upscope $end
$scope task check_count $end
$var reg 4 ' exp_count [3:0] $end
$var reg 80 ( test_name [79:0] $end
$upscope $end
$upscope $end
$enddefinitions $end
$comment Show the parameter values. $end
$dumpall
$end
#0
$dumpvars
bx (
bx '
bx &
1%
b0 $
0#
0"
bx !
$end
#5000
b0 !
b0 &
b0 '
b111001001100101011100110110010101110100 (
1"
#6000
0%
1#
#10000
0"
#15000
b1 !
b1 &
b1 $
b1 '
b1100011011011110111010101101110011101000101111100110001 (
1"
#20000
0"
#25000
b10 !
b10 &
b10 $
b10 '
b1100011011011110111010101101110011101000101111100110010 (
1"
#30000
0"
#35000
b11 !
b11 &
b11 $
b11 '
b1100011011011110111010101101110011101000101111100110011 (
1"
#36000
0#
#40000
0"
#45000
b1101000011011110110110001100100 (
1"
#46000
1%
1#
#50000
0"
#55000
b0 !
b0 &
b0 $
b0 '
b111001001100101011100110110010101110100 (
1"
