01_verilog_basics/02_combinational/src/full_adder.v
module full_adder(
    input a, b, cin,
    output cout,sum
);
    assign sum = a ^ b ^ cin;
    assign cout = (a & b) | (a & cin) | (b & cin);

endmodule

01_verilog_basics/04_testbench_practice/tb_refine/full_adder_tb_refine.v
`timescale 1ns/1ps

module full_adder_tb_refine;

    reg a, b, cin;

    wire sum, cout;

    reg expected_sum, expected_cout;

    full_adder dut (
        .a(a),
        .b(b),
        .cin(cin),
        .sum(sum),
        .cout(cout)
    );

    task run_test;
        input test_a;
        input test_b;
        input test_cin;
        input exp_sum;
        input exp_cout;

        begin
            a = test_a;
            b = test_b;
            cin = test_cin;
            expected_sum = exp_sum;
            expected_cout = exp_cout;

            #10;

            if (sum == expected_sum && cout == expected_cout) begin
                $display("pass | a=%b | b=%b | cin=%b | sum=%b | expected_sum=%b | cout=%b | expected_cout=%b",
                         a, b, cin, sum, expected_sum, cout, expected_cout);
            end else begin
                $display("fail | a=%b | b=%b | cin=%b | sum=%b | expected_sum=%b | cout=%b | expected_cout=%b",
                         a, b, cin, sum, expected_sum, cout, expected_cout);
            end
        end
    endtask

    initial begin
        $dumpfile("04_testbench_practice/waves/full_adder_tb_refine.vcd");
        $dumpvars(0, full_adder_tb_refine);

        $display("Refined FULL_ADDER Testbench with Expected Results");
        $display("---------------------------------------------------");

        // a + b + cin = {cout, sum}
        run_test(1'b0, 1'b0, 1'b0, 1'b0, 1'b0); // 0 + 0 + 0 = 00
        run_test(1'b0, 1'b0, 1'b1, 1'b1, 1'b0); // 0 + 0 + 1 = 01
        run_test(1'b0, 1'b1, 1'b0, 1'b1, 1'b0); // 0 + 1 + 0 = 01
        run_test(1'b0, 1'b1, 1'b1, 1'b0, 1'b1); // 0 + 1 + 1 = 10
        run_test(1'b1, 1'b0, 1'b0, 1'b1, 1'b0); // 1 + 0 + 0 = 01
        run_test(1'b1, 1'b0, 1'b1, 1'b0, 1'b1); // 1 + 0 + 1 = 10
        run_test(1'b1, 1'b1, 1'b0, 1'b0, 1'b1); // 1 + 1 + 0 = 10
        run_test(1'b1, 1'b1, 1'b1, 1'b1, 1'b1); // 1 + 1 + 1 = 11

        $finish;
    end

endmodule

01_verilog_basics/04_testbench_practice/waves/full_adder_tb_refine.vcd
$date
	Tue Jun 16 21:43:22 2026
$end
$version
	Icarus Verilog
$end
$timescale
	1ps
$end
$scope module full_adder_tb_refine $end
$var wire 1 ! sum $end
$var wire 1 " cout $end
$var reg 1 # a $end
$var reg 1 $ b $end
$var reg 1 % cin $end
$var reg 1 & expected_cout $end
$var reg 1 ' expected_sum $end
$scope module dut $end
$var wire 1 # a $end
$var wire 1 $ b $end
$var wire 1 % cin $end
$var wire 1 " cout $end
$var wire 1 ! sum $end
$upscope $end
$scope task run_test $end
$var reg 1 ( exp_cout $end
$var reg 1 ) exp_sum $end
$var reg 1 * test_a $end
$var reg 1 + test_b $end
$var reg 1 , test_cin $end
$upscope $end
$upscope $end
$enddefinitions $end
$comment Show the parameter values. $end
$dumpall
$end
#0
$dumpvars
0,
0+
0*
0)
0(
0'
0&
0%
0$
0#
0"
0!
$end
#10000
1!
1'
1%
1)
1,
#20000
0%
1$
0,
1+
#30000
1"
0!
1&
0'
1%
1(
0)
1,
#40000
0"
1!
0&
1'
0%
0$
1#
0(
1)
0,
0+
1*
#50000
1"
0!
1&
0'
1%
1(
0)
1,
#60000
0%
1$
0,
1+
#70000
1!
1'
1%
1)
1,
