01_verilog_basics/12_register_file_basic/src/register_file_basic.v
module register_file_basic(
    input clk,
    input reset,
    input write_en,
    input [1:0] write_addr,
    input [7:0] write_data,
    input [1:0] read_addr1,
    input [1:0] read_addr2,
    output [7:0] read_data1,
    output [7:0] read_data2
);

    reg [7:0] regs [0:3];

    integer i;

    always @(posedge clk) begin
        if (reset) begin
            for (i = 0; i < 4; i = i + 1) begin
                regs[i] <= 8'b00000000;
            end
        end else begin
            if (write_en) begin
                regs[write_addr] <= write_data;
            end
        end
    end

    assign read_data1 = regs[read_addr1];
    assign read_data2 = regs[read_addr2];

endmodule

01_verilog_basics/12_register_file_basic/tb/register_file_basic_tb.v
`timescale 1ns/1ps

module register_file_basic_tb;

    reg clk;
    reg reset;
    reg write_en;
    reg [1:0] write_addr;
    reg [7:0] write_data;
    reg [1:0] read_addr1;
    reg [1:0] read_addr2;

    wire [7:0] read_data1;
    wire [7:0] read_data2;

    register_file_basic dut (
        .clk(clk),
        .reset(reset),
        .write_en(write_en),
        .write_addr(write_addr),
        .write_data(write_data),
        .read_addr1(read_addr1),
        .read_addr2(read_addr2),
        .read_data1(read_data1),
        .read_data2(read_data2)
    );

    always #5 clk = ~clk;

    task write_reg;
        input [1:0] addr;
        input [7:0] data;
        input [8*60-1:0] test_name;

        begin
            write_en = 1'b1;
            write_addr = addr;
            write_data = data;

            @(posedge clk);
            #1;

            write_en = 1'b0;

            $display("WRITE: %s | addr = %0d, data = %h", test_name, addr, data);
        end
    endtask

    task check_read;
        input [1:0] addr1;
        input [1:0] addr2;
        input [7:0] expected1;
        input [7:0] expected2;
        input [8*60-1:0] test_name;

        begin
            read_addr1 = addr1;
            read_addr2 = addr2;

            #1;

            if (read_data1 === expected1 && read_data2 === expected2) begin
                $display("PASS: %s | read_data1 = %h, read_data2 = %h",
                         test_name, read_data1, read_data2);
            end else begin
                $display("FAIL: %s | expected1 = %h, actual1 = %h | expected2 = %h, actual2 = %h",
                         test_name, expected1, read_data1, expected2, read_data2);
            end
        end
    endtask

    initial begin
        $dumpfile("waves/register_file_basic.vcd");
        $dumpvars(0, register_file_basic_tb);

        clk = 0;
        reset = 0;
        write_en = 0;
        write_addr = 2'b00;
        write_data = 8'h00;
        read_addr1 = 2'b00;
        read_addr2 = 2'b00;

        reset = 1'b1;
        @(posedge clk);
        #1;
        reset = 1'b0;

        check_read(2'b00, 2'b01, 8'h00, 8'h00, "After reset, regs[0] and regs[1] should be 0");
        check_read(2'b10, 2'b11, 8'h00, 8'h00, "After reset, regs[2] and regs[3] should be 0");

        write_reg(2'b00, 8'hA1, "Write A1 to regs[0]");
        check_read(2'b00, 2'b00, 8'hA1, 8'hA1, "Read regs[0] from both read ports");

        write_reg(2'b01, 8'hB2, "Write B2 to regs[1]");
        check_read(2'b00, 2'b01, 8'hA1, 8'hB2, "Read regs[0] and regs[1]");

        write_reg(2'b10, 8'hC3, "Write C3 to regs[2]");
        write_reg(2'b11, 8'hD4, "Write D4 to regs[3]");
        check_read(2'b10, 2'b11, 8'hC3, 8'hD4, "Read regs[2] and regs[3]");

        check_read(2'b01, 2'b01, 8'hB2, 8'hB2, "Both read ports read regs[1]");

        write_reg(2'b00, 8'h5A, "Overwrite regs[0] with 5A");
        check_read(2'b00, 2'b01, 8'h5A, 8'hB2, "Read updated regs[0] and unchanged regs[1]");

        $display("Register file basic test completed.");
        $finish;
    end

endmodule

01_verilog_basics/12_register_file_basic/waves/register_file_basic.vcd
$date
	Thu Jul 09 21:51:57 2026
$end
$version
	Icarus Verilog
$end
$timescale
	1ps
$end
$scope module register_file_basic_tb $end
$var wire 8 ! read_data2 [7:0] $end
$var wire 8 " read_data1 [7:0] $end
$var reg 1 # clk $end
$var reg 2 $ read_addr1 [1:0] $end
$var reg 2 % read_addr2 [1:0] $end
$var reg 1 & reset $end
$var reg 2 ' write_addr [1:0] $end
$var reg 8 ( write_data [7:0] $end
$var reg 1 ) write_en $end
$scope module dut $end
$var wire 1 # clk $end
$var wire 2 * read_addr1 [1:0] $end
$var wire 2 + read_addr2 [1:0] $end
$var wire 8 , read_data1 [7:0] $end
$var wire 8 - read_data2 [7:0] $end
$var wire 1 & reset $end
$var wire 2 . write_addr [1:0] $end
$var wire 8 / write_data [7:0] $end
$var wire 1 ) write_en $end
$var integer 32 0 i [31:0] $end
$upscope $end
$scope task check_read $end
$var reg 2 1 addr1 [1:0] $end
$var reg 2 2 addr2 [1:0] $end
$var reg 8 3 expected1 [7:0] $end
$var reg 8 4 expected2 [7:0] $end
$var reg 480 5 test_name [479:0] $end
$upscope $end
$scope task write_reg $end
$var reg 2 6 addr [1:0] $end
$var reg 8 7 data [7:0] $end
$var reg 480 8 test_name [479:0] $end
$upscope $end
$upscope $end
$enddefinitions $end
$comment Show the parameter values. $end
$dumpall
$end
#0
$dumpvars
bx 8
bx 7
bx 6
bx 5
bx 4
bx 3
bx 2
bx 1
bx 0
b0 /
b0 .
bx -
bx ,
b0 +
b0 *
0)
b0 (
b0 '
1&
b0 %
b0 $
0#
bx "
bx !
$end
#5000
b0 "
b0 ,
b0 !
b0 -
b100 0
1#
#6000
b1 %
b1 +
b100000101100110011101000110010101110010001000000111001001100101011100110110010101110100001011000010000001110010011001010110011101110011010110110011000001011101001000000110000101101110011001000010000001110010011001010110011101110011010110110011000101011101001000000111001101101000011011110111010101101100011001000010000001100010011001010010000000110000 5
b0 4
b0 3
b1 2
b0 1
0&
#7000
b11 %
b11 +
b10 $
b10 *
b100000101100110011101000110010101110010001000000111001001100101011100110110010101110100001011000010000001110010011001010110011101110011010110110011001001011101001000000110000101101110011001000010000001110010011001010110011101110011010110110011001101011101001000000111001101101000011011110111010101101100011001000010000001100010011001010010000000110000 5
b11 2
b10 1
#8000
b10100001 (
b10100001 /
1)
b1010111011100100110100101110100011001010010000001000001001100010010000001110100011011110010000001110010011001010110011101110011010110110011000001011101 8
b10100001 7
b0 6
#10000
0#
#15000
1#
#16000
b10100001 !
b10100001 -
b0 %
b0 +
b10100001 "
b10100001 ,
b0 $
b0 *
b10100100110010101100001011001000010000001110010011001010110011101110011010110110011000001011101001000000110011001110010011011110110110100100000011000100110111101110100011010000010000001110010011001010110000101100100001000000111000001101111011100100111010001110011 5
b10100001 4
b10100001 3
b0 2
b0 1
0)
#17000
b10110010 (
b10110010 /
b1 '
b1 .
1)
b1010111011100100110100101110100011001010010000001000010001100100010000001110100011011110010000001110010011001010110011101110011010110110011000101011101 8
b10110010 7
b1 6
#20000
0#
#25000
1#
#26000
b10110010 !
b10110010 -
b1 %
b1 +
b10100100110010101100001011001000010000001110010011001010110011101110011010110110011000001011101001000000110000101101110011001000010000001110010011001010110011101110011010110110011000101011101 5
b10110010 4
b1 2
0)
#27000
b11000011 (
b11000011 /
b10 '
b10 .
1)
b1010111011100100110100101110100011001010010000001000011001100110010000001110100011011110010000001110010011001010110011101110011010110110011001001011101 8
b11000011 7
b10 6
#30000
0#
#35000
1#
#36000
b11010100 (
b11010100 /
b11 '
b11 .
b1010111011100100110100101110100011001010010000001000100001101000010000001110100011011110010000001110010011001010110011101110011010110110011001101011101 8
b11010100 7
b11 6
1)
#40000
0#
#45000
1#
#46000
b11010100 !
b11010100 -
b11 %
b11 +
b11000011 "
b11000011 ,
b10 $
b10 *
b10100100110010101100001011001000010000001110010011001010110011101110011010110110011001001011101001000000110000101101110011001000010000001110010011001010110011101110011010110110011001101011101 5
b11010100 4
b11000011 3
b11 2
b10 1
0)
#47000
b10110010 !
b10110010 -
b1 %
b1 +
b10110010 "
b10110010 ,
b1 $
b1 *
b1000010011011110111010001101000001000000111001001100101011000010110010000100000011100000110111101110010011101000111001100100000011100100110010101100001011001000010000001110010011001010110011101110011010110110011000101011101 5
b10110010 4
b10110010 3
b1 2
b1 1
#48000
b1011010 (
b1011010 /
b0 '
b0 .
1)
b1001111011101100110010101110010011101110111001001101001011101000110010100100000011100100110010101100111011100110101101100110000010111010010000001110111011010010111010001101000001000000011010101000001 8
b1011010 7
b0 6
#50000
0#
#55000
1#
#56000
b1011010 "
b1011010 ,
b0 $
b0 *
b10100100110010101100001011001000010000001110101011100000110010001100001011101000110010101100100001000000111001001100101011001110111001101011011001100000101110100100000011000010110111001100100001000000111010101101110011000110110100001100001011011100110011101100101011001000010000001110010011001010110011101110011010110110011000101011101 5
b1011010 3
b0 1
0)
