01_verilog_basics/08_sequence_detector/src/sequence_detector.v
module sequence_detector(
    input clk,
    input reset,
    input bit_in,
    output reg detected
);

    localparam S_IDLE = 3'b000;
    localparam S_1    = 3'b001;
    localparam S_10   = 3'b010;
    localparam S_101  = 3'b011;
    localparam S_1011 = 3'b100;

    reg [2:0] current_state;
    reg [2:0] next_state;

    always @(posedge clk) begin
        if (reset)
            current_state <= S_IDLE;
        else
            current_state <= next_state;
    end

    always @(*) begin
        next_state = current_state;

        case (current_state)
            S_IDLE: begin
                if (bit_in)
                    next_state = S_1;
                else
                    next_state = S_IDLE;
            end

            S_1: begin
                if (bit_in)
                    next_state = S_1;
                else
                    next_state = S_10; 
            end

            S_10: begin
                if (bit_in)
                    next_state = S_101;
                else
                    next_state = S_IDLE;
            end

            S_101: begin
                if (bit_in)
                    next_state = S_1011;
                else
                    next_state = S_10;
            end

            S_1011: begin
                if (bit_in)
                    next_state = S_1;
                else
                    next_state = S_10;
            end

            default: begin
                next_state = S_IDLE;
            end
        endcase
    end

    always @(*) begin
        detected = 1'b0;

        case (current_state)
            S_1011: begin
                detected = 1'b1;
            end

            default: begin
                detected = 1'b0;
            end
        endcase
    end

endmodule

01_verilog_basics/08_sequence_detector/tb/sequence_detector_tb.v
`timescale 1ns/1ps

module sequence_detector_tb;

    reg clk;
    reg reset;
    reg bit_in;

    wire detected;

    reg expected_detected;

    sequence_detector dut(
        .clk(clk),
        .reset(reset),
        .bit_in(bit_in),
        .detected(detected)
    );

    always #5 clk = ~clk;

    task check_detected;
        input input_bit;
        input expected_value;
        input [319:0] test_name;

        begin
            bit_in = input_bit;

            @(posedge clk);

            expected_detected = expected_value;

            #1;

            if (detected === expected_detected) begin
                $display("pass | %-30s | bit_in = %b | detected = %b",
                         test_name, bit_in, detected);
            end else begin
                $display("fail | %-30s | bit_in = %b | detected = %b | expected = %b",
                         test_name, bit_in, detected, expected_detected);
            end
        end
    endtask

    initial begin
        $dumpfile("waves/sequence_detector.vcd");
        $dumpvars(0, sequence_detector_tb);

        clk = 0;
        reset = 1;
        bit_in = 0;
        expected_detected = 0;

        @(posedge clk);
        reset = 0;

        // Test sequence: 1011011
        // Expected detections: after 1011 and after 1011011

        check_detected(1'b1, 1'b0, "Input 1");
        check_detected(1'b0, 1'b0, "Input 10");
        check_detected(1'b1, 1'b0, "Input 101");
        check_detected(1'b1, 1'b1, "Input 1011 detected");

        check_detected(1'b0, 1'b0, "Input 10110");
        check_detected(1'b1, 1'b0, "Input 101101");
        check_detected(1'b1, 1'b1, "Input 1011011 detected");

        $finish;
    end

endmodule

01_verilog_basics/08_sequence_detector/waves/sequence_detector.vcd
$date
	Mon Jun 29 23:38:25 2026
$end
$version
	Icarus Verilog
$end
$timescale
	1ps
$end
$scope module sequence_detector_tb $end
$var wire 1 ! detected $end
$var reg 1 " bit_in $end
$var reg 1 # clk $end
$var reg 1 $ expected_detected $end
$var reg 1 % reset $end
$scope module dut $end
$var wire 1 " bit_in $end
$var wire 1 # clk $end
$var wire 1 % reset $end
$var parameter 3 & S_1 $end
$var parameter 3 ' S_10 $end
$var parameter 3 ( S_101 $end
$var parameter 3 ) S_1011 $end
$var parameter 3 * S_IDLE $end
$var reg 3 + current_state [2:0] $end
$var reg 1 ! detected $end
$var reg 3 , next_state [2:0] $end
$upscope $end
$scope task check_detected $end
$var reg 1 - expected_value $end
$var reg 1 . input_bit $end
$var reg 320 / test_name [319:0] $end
$upscope $end
$upscope $end
$enddefinitions $end
$comment Show the parameter values. $end
$dumpall
b0 *
b100 )
b11 (
b10 '
b1 &
$end
#0
$dumpvars
bx /
x.
x-
b0 ,
bx +
1%
0$
0#
0"
x!
$end
#5000
0!
b0 +
b1 ,
1"
b1001001011011100111000001110101011101000010000000110001 /
0-
1.
0%
1#
#10000
0#
#15000
b1 +
1#
#16000
b10 ,
0"
b100100101101110011100000111010101110100001000000011000100110000 /
0.
#20000
0#
#25000
b0 ,
b10 +
1#
#26000
b11 ,
1"
b10010010110111001110000011101010111010000100000001100010011000000110001 /
1.
#30000
0#
#35000
b100 ,
b11 +
1#
#36000
b1001001011011100111000001110101011101000010000000110001001100000011000100110001001000000110010001100101011101000110010101100011011101000110010101100100 /
1-
#40000
0#
#45000
1!
b1 ,
b100 +
1$
1#
#46000
b10 ,
0"
b100100101101110011100000111010101110100001000000011000100110000001100010011000100110000 /
0-
0.
#50000
0#
#55000
0!
b0 ,
b10 +
0$
1#
#56000
b11 ,
1"
b10010010110111001110000011101010111010000100000001100010011000000110001001100010011000000110001 /
1.
#60000
0#
#65000
b100 ,
b11 +
1#
#66000
b1001001011011100111000001110101011101000010000000110001001100000011000100110001001100000011000100110001001000000110010001100101011101000110010101100011011101000110010101100100 /
1-
#70000
0#
#75000
1!
b1 ,
b100 +
1$
1#
