01_verilog_basics/09_simple_fifo/src/simple_fifo.v
module simple_fifo (
    input clk,
    input reset,
    input write_en,
    input read_en,
    input [7:0] data_in,
    output reg [7:0] data_out,
    output full,
    output empty
);

    reg [7:0] mem [0:3];

    reg [1:0] write_ptr;
    reg [1:0] read_ptr;

    reg [2:0] count;

    wire valid_write;
    wire valid_read;

    assign full  = (count == 4);
    assign empty = (count == 0);

    assign valid_write = write_en && !full;
    assign valid_read  = read_en && !empty;

        always @(posedge clk) begin
        if (reset) begin
            write_ptr <= 2'b00;
            read_ptr  <= 2'b00;
            count     <= 3'b000;
            data_out  <= 8'b00000000;
        end
        else begin
            if (valid_write) begin
                mem[write_ptr] <= data_in;
                write_ptr <= write_ptr + 1;
            end

            if (valid_read) begin
                data_out <= mem[read_ptr];
                read_ptr <= read_ptr + 1;
            end

            case ({valid_write, valid_read})
                2'b10: count <= count + 1;
                2'b01: count <= count - 1;
                2'b11: count <= count;
                2'b00: count <= count;
            endcase
        end
    end

endmodule

01_verilog_basics/09_simple_fifo/tb/simple_fifo_tb.v
`timescale 1ns/1ps

module simple_fifo_tb;

    reg clk;
    reg reset;
    reg write_en;
    reg read_en;
    reg [7:0] data_in;

    wire [7:0] data_out;
    wire full;
    wire empty;

    reg [7:0] expected_data;

    simple_fifo dut (
        .clk(clk),
        .reset(reset),
        .write_en(write_en),
        .read_en(read_en),
        .data_in(data_in),
        .data_out(data_out),
        .full(full),
        .empty(empty)
    );

    always #5 clk = ~clk;

    task check_flags;
        input expected_full;
        input expected_empty;
        input [319:0] test_name;

        begin
            #1;

            if (full === expected_full && empty === expected_empty) begin
                $display("pass | %-40s | full = %b | empty = %b",
                         test_name, full, empty);
            end else begin
                $display("fail | %-40s | full = %b | expected_full = %b | empty = %b | expected_empty = %b",
                         test_name, full, expected_full, empty, expected_empty);
            end
        end
    endtask

    task write_fifo;
        input [7:0] input_data;
        input expected_full;
        input expected_empty;
        input [319:0] test_name;

        begin
            data_in = input_data;
            write_en = 1;
            read_en = 0;

            @(posedge clk);

            #1;

            if (full === expected_full && empty === expected_empty) begin
                $display("pass | %-40s | write data = %h | full = %b | empty = %b",
                         test_name, input_data, full, empty);
            end else begin
                $display("fail | %-40s | write data = %h | full = %b | expected_full = %b | empty = %b | expected_empty = %b",
                         test_name, input_data, full, expected_full, empty, expected_empty);
            end

            write_en = 0;
        end
    endtask

    task read_fifo;
        input [7:0] expected_value;
        input expected_full;
        input expected_empty;
        input [319:0] test_name;

        begin
            write_en = 0;
            read_en = 1;

            @(posedge clk);

            expected_data = expected_value;

            #1;

            if (data_out === expected_data && full === expected_full && empty === expected_empty) begin
                $display("pass | %-40s | data_out = %h | full = %b | empty = %b",
                         test_name, data_out, full, empty);
            end else begin
                $display("fail | %-40s | data_out = %h | expected_data = %h | full = %b | expected_full = %b | empty = %b | expected_empty = %b",
                         test_name, data_out, expected_data, full, expected_full, empty, expected_empty);
            end

            read_en = 0;
        end
    endtask

    task read_when_empty;
        input expected_full;
        input expected_empty;
        input [319:0] test_name;

        begin
            write_en = 0;
            read_en = 1;

            @(posedge clk);

            #1;

            if (full === expected_full && empty === expected_empty) begin
                $display("pass | %-40s | full = %b | empty = %b",
                         test_name, full, empty);
            end else begin
                $display("fail | %-40s | full = %b | expected_full = %b | empty = %b | expected_empty = %b",
                         test_name, full, expected_full, empty, expected_empty);
            end

            read_en = 0;
        end
    endtask

    initial begin
        $dumpfile("waves/simple_fifo.vcd");
        $dumpvars(0, simple_fifo_tb);

        clk = 0;
        reset = 1;
        write_en = 0;
        read_en = 0;
        data_in = 8'h00;
        expected_data = 8'h00;

        @(posedge clk);
        #1;
        reset = 0;

        check_flags(1'b0, 1'b1, "After reset, FIFO should be empty");

        // Basic write and read test
        write_fifo(8'hA1, 1'b0, 1'b0, "Write A1");
        write_fifo(8'hB2, 1'b0, 1'b0, "Write B2");

        read_fifo(8'hA1, 1'b0, 1'b0, "Read first value, expect A1");
        read_fifo(8'hB2, 1'b0, 1'b1, "Read second value, expect B2");

        // Fill FIFO
        write_fifo(8'h11, 1'b0, 1'b0, "Fill FIFO: write 11");
        write_fifo(8'h22, 1'b0, 1'b0, "Fill FIFO: write 22");
        write_fifo(8'h33, 1'b0, 1'b0, "Fill FIFO: write 33");
        write_fifo(8'h44, 1'b1, 1'b0, "Fill FIFO: write 44, FIFO should be full");

        // Overflow attempt
        write_fifo(8'h55, 1'b1, 1'b0, "Attempt overflow write 55");

        // Read all data after overflow attempt
        read_fifo(8'h11, 1'b0, 1'b0, "Read after overflow, expect 11");
        read_fifo(8'h22, 1'b0, 1'b0, "Read after overflow, expect 22");
        read_fifo(8'h33, 1'b0, 1'b0, "Read after overflow, expect 33");
        read_fifo(8'h44, 1'b0, 1'b1, "Read after overflow, expect 44");

        // Underflow attempt
        read_when_empty(1'b0, 1'b1, "Attempt underflow read");

        $finish;
    end

endmodule

01_verilog_basics/09_simple_fifo/waves/simple_fifo.vcd
$date
	Thu Jul 02 23:14:36 2026
$end
$version
	Icarus Verilog
$end
$timescale
	1ps
$end
$scope module simple_fifo_tb $end
$var wire 1 ! full $end
$var wire 1 " empty $end
$var wire 8 # data_out [7:0] $end
$var reg 1 $ clk $end
$var reg 8 % data_in [7:0] $end
$var reg 8 & expected_data [7:0] $end
$var reg 1 ' read_en $end
$var reg 1 ( reset $end
$var reg 1 ) write_en $end
$scope module dut $end
$var wire 1 $ clk $end
$var wire 8 * data_in [7:0] $end
$var wire 1 ' read_en $end
$var wire 1 ( reset $end
$var wire 1 + valid_read $end
$var wire 1 , valid_write $end
$var wire 1 ) write_en $end
$var wire 1 ! full $end
$var wire 1 " empty $end
$var reg 3 - count [2:0] $end
$var reg 8 . data_out [7:0] $end
$var reg 2 / read_ptr [1:0] $end
$var reg 2 0 write_ptr [1:0] $end
$upscope $end
$scope task check_flags $end
$var reg 1 1 expected_empty $end
$var reg 1 2 expected_full $end
$var reg 320 3 test_name [319:0] $end
$upscope $end
$scope task read_fifo $end
$var reg 1 4 expected_empty $end
$var reg 1 5 expected_full $end
$var reg 8 6 expected_value [7:0] $end
$var reg 320 7 test_name [319:0] $end
$upscope $end
$scope task read_when_empty $end
$var reg 1 8 expected_empty $end
$var reg 1 9 expected_full $end
$var reg 320 : test_name [319:0] $end
$upscope $end
$scope task write_fifo $end
$var reg 1 ; expected_empty $end
$var reg 1 < expected_full $end
$var reg 8 = input_data [7:0] $end
$var reg 320 > test_name [319:0] $end
$upscope $end
$upscope $end
$enddefinitions $end
$comment Show the parameter values. $end
$dumpall
$end
#0
$dumpvars
bx >
bx =
x<
x;
bx :
x9
x8
bx 7
bx 6
x5
x4
bx 3
x2
x1
bx 0
bx /
bx .
bx -
0,
0+
b0 *
0)
1(
0'
b0 &
b0 %
0$
bx #
x"
x!
$end
#5000
b0 #
b0 .
0!
1"
b0 -
b0 /
b0 0
1$
#6000
b10000010110011001110100011001010111001000100000011100100110010101110011011001010111010000101100001000000100011001001001010001100100111100100000011100110110100001101111011101010110110001100100001000000110001001100101001000000110010101101101011100000111010001111001 3
11
02
0(
#7000
1,
1)
b10100001 %
b10100001 *
b101011101110010011010010111010001100101001000000100000100110001 >
0;
0<
b10100001 =
#10000
0$
#15000
0"
b1 -
b1 0
1$
#16000
b10110010 %
b10110010 *
b101011101110010011010010111010001100101001000000100001000110010 >
b10110010 =
1)
#20000
0$
#25000
b10 -
b10 0
1$
#26000
1+
0,
1'
b10100100110010101100001011001000010000001100110011010010111001001110011011101000010000001110110011000010110110001110101011001010010110000100000011001010111100001110000011001010110001101110100001000000100000100110001 7
04
05
b10100001 6
0)
#30000
0$
#35000
b1 -
b1 /
b10100001 #
b10100001 .
b10100001 &
1$
#36000
b1010010011001010110000101100100001000000111001101100101011000110110111101101110011001000010000001110110011000010110110001110101011001010010110000100000011001010111100001110000011001010110001101110100001000000100001000110010 7
14
b10110010 6
1'
#40000
0$
#45000
0+
1"
b0 -
b10 /
b10110010 #
b10110010 .
b10110010 &
1$
#46000
1,
1)
b10001 %
b10001 *
b1000110011010010110110001101100001000000100011001001001010001100100111100111010001000000111011101110010011010010111010001100101001000000011000100110001 >
b10001 =
0'
#50000
0$
#55000
0"
b1 -
b11 0
1$
#56000
b100010 %
b100010 *
b1000110011010010110110001101100001000000100011001001001010001100100111100111010001000000111011101110010011010010111010001100101001000000011001000110010 >
b100010 =
1)
#60000
0$
#65000
b10 -
b0 0
1$
#66000
b110011 %
b110011 *
b1000110011010010110110001101100001000000100011001001001010001100100111100111010001000000111011101110010011010010111010001100101001000000011001100110011 >
b110011 =
1)
#70000
0$
#75000
b11 -
b1 0
1$
#76000
b1000100 %
b1000100 *
b1000110011010010110110001101100001000000100011001001001010001100100111100111010001000000111011101110010011010010111010001100101001000000011010000110100001011000010000001000110010010010100011001001111001000000111001101101000011011110111010101101100011001000010000001100010011001010010000001100110011101010110110001101100 >
1<
b1000100 =
1)
#80000
0$
#85000
0,
1!
b100 -
b10 0
1$
#86000
b1010101 %
b1010101 *
b1000001011101000111010001100101011011010111000001110100001000000110111101110110011001010111001001100110011011000110111101110111001000000111011101110010011010010111010001100101001000000011010100110101 >
b1010101 =
1)
#90000
0$
#95000
1$
#96000
1+
1'
b10100100110010101100001011001000010000001100001011001100111010001100101011100100010000001101111011101100110010101110010011001100110110001101111011101110010110000100000011001010111100001110000011001010110001101110100001000000011000100110001 7
04
b10001 6
0)
#100000
0$
#105000
0!
b11 -
b11 /
b10001 #
b10001 .
b10001 &
1$
#106000
b10100100110010101100001011001000010000001100001011001100111010001100101011100100010000001101111011101100110010101110010011001100110110001101111011101110010110000100000011001010111100001110000011001010110001101110100001000000011001000110010 7
b100010 6
1'
#110000
0$
#115000
b10 -
b0 /
b100010 #
b100010 .
b100010 &
1$
#116000
b10100100110010101100001011001000010000001100001011001100111010001100101011100100010000001101111011101100110010101110010011001100110110001101111011101110010110000100000011001010111100001110000011001010110001101110100001000000011001100110011 7
b110011 6
1'
#120000
0$
#125000
b1 -
b1 /
b110011 #
b110011 .
b110011 &
1$
#126000
b10100100110010101100001011001000010000001100001011001100111010001100101011100100010000001101111011101100110010101110010011001100110110001101111011101110010110000100000011001010111100001110000011001010110001101110100001000000011010000110100 7
14
b1000100 6
1'
#130000
0$
#135000
0+
1"
b0 -
b10 /
b1000100 #
b1000100 .
b1000100 &
1$
#136000
b1000001011101000111010001100101011011010111000001110100001000000111010101101110011001000110010101110010011001100110110001101111011101110010000001110010011001010110000101100100 :
18
09
1'
#140000
0$
#145000
1$
#146000
0'
