01_verilog_basics/02_combinational/src/mux2to1.v
module mux2to1(
    input a,
    input b,
    input sel,
    output y
);

    assign y = sel ? a : b;

endmodule

01_verilog_basics/02_combinational/tb/mux2to1_tb.v
`timescale 1ns/1ps

module mux2to1_tb;

reg a, b, sel;
wire y;

mux2to1 uut (
    .a(a),
    .b(b),
    .sel(sel),
    .y(y)
);

initial begin
    $dumpfile("waveforms/mux2to1.vcd");
    $dumpvars(0, mux2to1_tb);

    a = 0; b = 0; sel = 0; #10;
    a = 0; b = 0; sel = 1; #10;
    a = 1; b = 0; sel = 0; #10;
    a = 1; b = 0; sel = 1; #10;
    a = 0; b = 1; sel = 0; #10;
    a = 0; b = 1; sel = 1; #10;
    a = 1; b = 1; sel = 0; #10;
    a = 1; b = 1; sel = 1; #10;

    $finish;
end

endmodule

01_verilog_basics/02_combinational/waveforms/mux2to1.vcd
$date
	Sun Jun 14 16:18:52 2026
$end
$version
	Icarus Verilog
$end
$timescale
	1ps
$end
$scope module mux2to1_tb $end
$var wire 1 ! y $end
$var reg 1 " a $end
$var reg 1 # b $end
$var reg 1 $ sel $end
$scope module uut $end
$var wire 1 " a $end
$var wire 1 # b $end
$var wire 1 $ sel $end
$var wire 1 ! y $end
$upscope $end
$upscope $end
$enddefinitions $end
$comment Show the parameter values. $end
$dumpall
$end
#0
$dumpvars
0$
0#
0"
0!
$end
#10000
1$
#20000
0$
1"
#30000
1!
1$
#40000
0$
1#
0"
#50000
0!
1$
#60000
1!
0$
1"
#70000
1$
