01_verilog_basics/07_fsm_traffic_light/src/traffic_light_fsm.v
module traffic_light_fsm(
    input clk,
    input reset,
    input timer_done,
    output reg [1:0] ns_light,
    output reg [1:0] ew_light
);

    localparam RED    = 2'b00;
    localparam YELLOW = 2'b01;
    localparam GREEN  = 2'b10;

    localparam S_NS_GREEN  = 2'b00;
    localparam S_NS_YELLOW = 2'b01;
    localparam S_EW_GREEN  = 2'b10;
    localparam S_EW_YELLOW = 2'b11;

    reg [1:0] current_state;
    reg [1:0] next_state;

    always @(posedge clk) begin
        if (reset)
            current_state <= S_NS_GREEN;
        else
            current_state <= next_state;
    end

    always @(*) begin
        next_state = current_state;

        case (current_state)
            S_NS_GREEN: begin
                if (timer_done)
                    next_state = S_NS_YELLOW;
            end

            S_NS_YELLOW: begin
                if (timer_done)
                    next_state = S_EW_GREEN;
            end

            S_EW_GREEN: begin
                if (timer_done)
                    next_state = S_EW_YELLOW;
            end

            S_EW_YELLOW: begin
                if (timer_done)
                    next_state = S_NS_GREEN;
            end

            default: begin
                next_state = S_NS_GREEN;
            end
        endcase
    end

    always @(*) begin
        ns_light = RED;
        ew_light = RED;

        case (current_state)
            S_NS_GREEN: begin
                ns_light = GREEN;
                ew_light = RED;
            end

            S_NS_YELLOW: begin
                ns_light = YELLOW;
                ew_light = RED;
            end

            S_EW_GREEN: begin
                ns_light = RED;
                ew_light = GREEN;
            end

            S_EW_YELLOW: begin
                ns_light = RED;
                ew_light = YELLOW;
            end

            default: begin
                ns_light = GREEN;
                ew_light = RED;
            end
        endcase
    end

endmodule

01_verilog_basics/07_fsm_traffic_light/tb/traffic_light_fsm_tb.v
`timescale 1ns/1ps

module traffic_light_fsm_tb;

    reg clk;
    reg reset;
    reg timer_done;

    wire [1:0] ns_light;
    wire [1:0] ew_light;

    localparam RED = 2'b00;
    localparam YELLOW = 2'b01;
    localparam GREEN = 2'b10;

    traffic_light_fsm dut(
        .clk(clk),
        .reset(reset),
        .timer_done(timer_done),
        .ns_light(ns_light),
        .ew_light(ew_light)
    );

    always #5 clk = ~clk;

    task check_lights;
        input [1:0] exp_ns;
        input [1:0] exp_ew;
        input [319:0] test_name;

        begin
            #1;

            if (ns_light == exp_ns && ew_light == exp_ew) begin
                $display ("pass | %-s | ns_light is %b | ew_light is %b", 
                          test_name, ns_light, ew_light);
            end else begin
                 $display("fail | %-s | ns_light is %b | ew_light is %b | expected_ns is %b | expected_ew is %b",
                         test_name, ns_light, ew_light, exp_ns, exp_ew);
            end
        end
    endtask

    initial begin
        $dumpfile("waves/traffic_light_fsm.vcd");
        $dumpvars(0, traffic_light_fsm_tb);
        
        clk = 0;
        reset = 1;
        timer_done = 0;

        @(posedge clk);
        check_lights(GREEN, RED, "Reset to S_NS_GREEN");

        reset = 0;

        @(posedge clk);
        check_lights(GREEN, RED, "Hold S_NS_GREEN");

        timer_done = 1;
        @(posedge clk);
        check_lights(YELLOW, RED, "S_NS_GREEN to S_NS_YELLOW");

        timer_done = 0;
        @(posedge clk);
        check_lights(YELLOW, RED, "Hold S_NS_YELLOW");

        timer_done = 1;
        @(posedge clk);
        check_lights(RED, GREEN, "S_NS_YELLOW to S_EW_GREEN");

        timer_done = 0;
        @(posedge clk);
        check_lights(RED, GREEN, "Hold S_EW_GREEN");

        timer_done = 1;
        @(posedge clk);
        check_lights(RED, YELLOW, "S_EW_GREEN to S_EW_YELLOW");

        timer_done = 0;
        @(posedge clk);
        check_lights(RED, YELLOW, "Hold S_EW_YELLOW");

        timer_done = 1;
        @(posedge clk);
        check_lights(GREEN, RED, "S_EW_YELLOW to S_NS_GREEN");

        timer_done = 0;
        @(posedge clk);
        check_lights(GREEN, RED, "Hold S_NS_GREEN again");

        $finish;
    end

endmodule

01_verilog_basics/07_fsm_traffic_light/waves/traffic_light_fsm.vcd
$date
	Fri Jun 26 22:12:54 2026
$end
$version
	Icarus Verilog
$end
$timescale
	1ps
$end
$scope module traffic_light_fsm_tb $end
$var wire 2 ! ns_light [1:0] $end
$var wire 2 " ew_light [1:0] $end
$var parameter 2 # GREEN $end
$var parameter 2 $ RED $end
$var parameter 2 % YELLOW $end
$var reg 1 & clk $end
$var reg 1 ' reset $end
$var reg 1 ( timer_done $end
$scope module dut $end
$var wire 1 & clk $end
$var wire 1 ' reset $end
$var wire 1 ( timer_done $end
$var parameter 2 ) GREEN $end
$var parameter 2 * RED $end
$var parameter 2 + S_EW_GREEN $end
$var parameter 2 , S_EW_YELLOW $end
$var parameter 2 - S_NS_GREEN $end
$var parameter 2 . S_NS_YELLOW $end
$var parameter 2 / YELLOW $end
$var reg 2 0 current_state [1:0] $end
$var reg 2 1 ew_light [1:0] $end
$var reg 2 2 next_state [1:0] $end
$var reg 2 3 ns_light [1:0] $end
$upscope $end
$scope task check_lights $end
$var reg 2 4 exp_ew [1:0] $end
$var reg 2 5 exp_ns [1:0] $end
$var reg 320 6 test_name [319:0] $end
$upscope $end
$upscope $end
$enddefinitions $end
$comment Show the parameter values. $end
$dumpall
b1 /
b1 .
b0 -
b11 ,
b10 +
b0 *
b10 )
b1 %
b0 $
b10 #
$end
#0
$dumpvars
bx 6
bx 5
bx 4
bx 3
b0 2
bx 1
bx 0
0(
1'
0&
bx "
bx !
$end
#5000
b0 "
b0 1
b10 !
b10 3
b0 0
b1010010011001010111001101100101011101000010000001110100011011110010000001010011010111110100111001010011010111110100011101010010010001010100010101001110 6
b0 4
b10 5
1&
#6000
0'
#10000
0&
#15000
b10010000110111101101100011001000010000001010011010111110100111001010011010111110100011101010010010001010100010101001110 6
1&
#16000
b1 2
1(
#20000
0&
#25000
b1 !
b1 3
b10 2
b1 0
b1010011010111110100111001010011010111110100011101010010010001010100010101001110001000000111010001101111001000000101001101011111010011100101001101011111010110010100010101001100010011000100111101010111 6
b1 5
1&
#26000
b1 2
0(
#30000
0&
#35000
b1001000011011110110110001100100001000000101001101011111010011100101001101011111010110010100010101001100010011000100111101010111 6
1&
#36000
b10 2
1(
#40000
0&
#45000
b10 "
b10 1
b0 !
b0 3
b11 2
b10 0
b1010011010111110100111001010011010111110101100101000101010011000100110001001111010101110010000001110100011011110010000001010011010111110100010101010111010111110100011101010010010001010100010101001110 6
b10 4
b0 5
1&
#46000
b10 2
0(
#50000
0&
#55000
b10010000110111101101100011001000010000001010011010111110100010101010111010111110100011101010010010001010100010101001110 6
1&
#56000
b11 2
1(
#60000
0&
#65000
b1 "
b1 1
b0 2
b11 0
b1010011010111110100010101010111010111110100011101010010010001010100010101001110001000000111010001101111001000000101001101011111010001010101011101011111010110010100010101001100010011000100111101010111 6
b1 4
1&
#66000
b11 2
0(
#70000
0&
#75000
b1001000011011110110110001100100001000000101001101011111010001010101011101011111010110010100010101001100010011000100111101010111 6
1&
#76000
b0 2
1(
#80000
0&
#85000
b10 !
b10 3
b0 "
b0 1
b1 2
b0 0
b1010011010111110100010101010111010111110101100101000101010011000100110001001111010101110010000001110100011011110010000001010011010111110100111001010011010111110100011101010010010001010100010101001110 6
b0 4
b10 5
1&
#86000
b0 2
0(
#90000
0&
#95000
b10010000110111101101100011001000010000001010011010111110100111001010011010111110100011101010010010001010100010101001110001000000110000101100111011000010110100101101110 6
1&
